subrepo.py
git_subrepo-0.4.6.post1.data/scripts/git-subrepo-init.bat
git_subrepo-0.4.6.post1.data/scripts/git-subrepo-init.ps1
git_subrepo-0.4.6.post1.data/scripts/git-subrepo-init.sh
subrepo/.rc
subrepo/Changes
subrepo/Intro.pod
subrepo/License
subrepo/Makefile
subrepo/Meta
subrepo/ReadMe.pod
subrepo/ext/bashplus/.gitrepo
subrepo/ext/bashplus/.travis.yml
subrepo/ext/bashplus/Changes
subrepo/ext/bashplus/License
subrepo/ext/bashplus/Makefile
subrepo/ext/bashplus/Meta
subrepo/ext/bashplus/ReadMe.pod
subrepo/ext/bashplus/bin/bash+
subrepo/ext/bashplus/doc/bash+.swim
subrepo/ext/bashplus/lib/bash+.bash
subrepo/ext/bashplus/man/man1/bash+.1
subrepo/ext/bashplus/man/man3/bash+.3
subrepo/lib/git-subrepo
subrepo/lib/git-subrepo.d/bash+.bash
subrepo/lib/git-subrepo.d/help-functions.bash
subrepo/man/man1/git-subrepo.1
subrepo/share/completion.bash
subrepo/share/enable-completion.sh
subrepo/share/git-completion.bash
subrepo/share/zsh-completion/_git-subrepo
git_subrepo-0.4.6.post1.dist-info/LICENSE
git_subrepo-0.4.6.post1.dist-info/METADATA
git_subrepo-0.4.6.post1.dist-info/WHEEL
git_subrepo-0.4.6.post1.dist-info/entry_points.txt
git_subrepo-0.4.6.post1.dist-info/top_level.txt
git_subrepo-0.4.6.post1.dist-info/RECORD
